pynetworks/__init__.py
pynetworks/dot.py
pynetworks/networks.py
pynetworks/pathfinding.py
pynetworks-0.6.1.dist-info/LICENSE
pynetworks-0.6.1.dist-info/METADATA
pynetworks-0.6.1.dist-info/WHEEL
pynetworks-0.6.1.dist-info/top_level.txt
pynetworks-0.6.1.dist-info/RECORD
