Metadata-Version: 2.1
Name: pynetworks
Version: 0.6.1
Summary: A Python implementation for networks of nodes.
Home-page: UNKNOWN
Author: Thomas Breydo
Author-email: tbreydo@gmail.com
License: UNKNOWN
Project-URL: Documentation, https://pynetworks.readthedocs.io
Project-URL: Code, https://github.com/thomasbreydo/pynetworks
Platform: UNKNOWN
Classifier: Development Status :: 5 - Production/Stable
Classifier: License :: OSI Approved :: GNU General Public License v3 (GPLv3)
Classifier: Operating System :: OS Independent
Classifier: Programming Language :: Python
Classifier: Topic :: Scientific/Engineering :: Mathematics
Requires-Dist: pyperclip (>=1.8.0)
